Metadata-Version: 2.1
Name: interframe-subtraction
Version: 0.0.2
Summary: A module to call MATLAB from Python
Home-page: http://www.mathworks.com/
Author: MathWorks
Platform: Linux
Platform: Windows
Platform: MacOS
